{
  "scheming_version": 1,
  "dataset_type": "all",
  "dataset_fields": [
    {
      "field_name": "geoserver_link_enabled",
      "harmonized_field_name": "geoserver_link_enabled",
      "preset": "select",
      "choices": [
        {
          "value": "False",
          "label": {
            "en": "False",
            "nl": "Nee",
            "sv": "Nej"
          }
        },
        {
          "value": "True",
          "label": {
            "en": "True",
            "nl": "Ja",
            "sv": "Ja"
          }
        }
      ],
      "label": {
        "en": "Link to Geoserver",
        "nl": "Publiceren Geoserver",
        "sv": "Länk till Geoserver"
      },
      "help_inline": true,
      "help_text": {
        "en": "Links to Geoserver",
        "nl": "Linkt naar Geoserver",
        "sv": "Länkar till Geoserver"
      },
      "default_value":"False",
      "required": true
    }
  ],
  "resource_fields": [
    {
      "field_name": "timestamp_identifier",
      "label": {
        "en": "Time series column",
        "nl": "Time series kolom",
        "sv": "Time series kolumn"
      },
      "help_text": {
        "en": "Populate with the column name containing timestamps, to enable time series filtering functionality on the map viewer",
        "nl": "Vul de kolomnaam in van de timestamp kolom, om de time series functionaliteit in de kaart te activeren",
        "sv": "Fyll i kolumnnamnet som innehåller tidsstämplar för att aktivera tidsseriefiltreringsfunktioner i kartvisaren"
      },
      "form_snippet": "text.html"
    },
    {
      "field_name": "wms_url",
      "display_snippet": null,
      "form_snippet": "text.html",
      "classes": ["hidden"]
    },
    {
      "field_name": "wfs_url",
      "display_snippet": null,
      "form_snippet": "text.html",
      "classes": ["hidden"]
    }
    ]
}